jais/__init__.py
jais/__main__.py
jais/main.py
jais/models/business.py
jais_search-0.1.3.dist-info/METADATA
jais_search-0.1.3.dist-info/WHEEL
jais_search-0.1.3.dist-info/entry_points.txt
jais_search-0.1.3.dist-info/RECORD
